medimeta/__init__.py
medimeta/batches.py
medimeta/logger.py
medimeta/medimeta.py
medimeta/task_presampling.py
medimeta/tasks.py
medimeta-0.0.6.dist-info/METADATA
medimeta-0.0.6.dist-info/WHEEL
medimeta-0.0.6.dist-info/licenses/LICENSE
medimeta-0.0.6.dist-info/licenses/LICENSE.LESSER
medimeta-0.0.6.dist-info/RECORD
