Metadata-Version: 2.3
Name: medimeta
Version: 0.0.6
Summary: Library for using the MedIMeta dataset
Project-URL: Homepage, https://github.com/StefanoWoerner/medimeta-pytorch
Project-URL: Issue Tracker, https://github.com/StefanoWoerner/medimeta-pytorch/issues
Author-email: Stefano Woerner <stefano@woerner.eu>
License-File: LICENSE
License-File: LICENSE.LESSER
Classifier: Intended Audience :: Developers
Classifier: Intended Audience :: Education
Classifier: Intended Audience :: Science/Research
Classifier: License :: OSI Approved :: GNU Lesser General Public License v3 (LGPLv3)
Classifier: Operating System :: OS Independent
Classifier: Programming Language :: Python :: 3
Classifier: Programming Language :: Python :: 3.10
Classifier: Programming Language :: Python :: 3.11
Classifier: Programming Language :: Python :: 3.12
Classifier: Topic :: Scientific/Engineering
Classifier: Topic :: Scientific/Engineering :: Artificial Intelligence
Requires-Python: >=3.10
Requires-Dist: h5py>=3.8.0
Requires-Dist: numpy>=1.24.3
Requires-Dist: pillow>=9.5.0
Requires-Dist: pyyaml>=6.0
Requires-Dist: torch>=2.0.0
Requires-Dist: torchcross>=0.0.6
Requires-Dist: torchvision>=0.15.1
